elasticsearch_logging/__init__.py
elasticsearch_logging/logger.py
elasticsearch_logging-0.1.0.dist-info/LICENSE
elasticsearch_logging-0.1.0.dist-info/METADATA
elasticsearch_logging-0.1.0.dist-info/WHEEL
elasticsearch_logging-0.1.0.dist-info/top_level.txt
elasticsearch_logging-0.1.0.dist-info/RECORD
