Metadata-Version: 2.1
Name: elasticsearch-logging
Version: 0.1.0
Summary: Elasticsearch logging
Home-page: https://github.com/XDeepZeroX/elasticsearch-logging
Author: XDeepZeroX
License: MIT
Keywords: logging,es,elastic search
Platform: all
Classifier: Development Status :: 5 - Production/Stable
Classifier: Intended Audience :: Developers
Classifier: License :: OSI Approved :: MIT License
Classifier: Operating System :: OS Independent
Classifier: Programming Language :: Python :: 3
Classifier: Programming Language :: Python :: 3.10
Classifier: Topic :: Internet :: WWW/HTTP
Classifier: Topic :: Software Development :: Libraries :: Python Modules
Classifier: Topic :: System :: Logging
Requires-Python: >=3.8, <4
License-File: LICENSE
Requires-Dist: elasticsearch (>=8.3.3)
Provides-Extra: dev
Requires-Dist: pep8-naming (==0.13.1) ; extra == 'dev'
Requires-Dist: flake8 (==4.0.1) ; extra == 'dev'
Requires-Dist: flake8-annotations (==2.9.1) ; extra == 'dev'
Requires-Dist: flake8-annotations-coverage (==0.0.6) ; extra == 'dev'
Requires-Dist: flake8-bugbear (==22.7.1) ; extra == 'dev'
Requires-Dist: flake8-builtins (==1.5.3) ; extra == 'dev'
Requires-Dist: flake8-class-attributes-order (==0.1.3) ; extra == 'dev'
Requires-Dist: flake8-cognitive-complexity (==0.1.0) ; extra == 'dev'
Requires-Dist: flake8-commas (==2.1.0) ; extra == 'dev'
Requires-Dist: flake8-comprehensions (==3.10.0) ; extra == 'dev'
Requires-Dist: flake8-docstrings (==1.6.0) ; extra == 'dev'
Requires-Dist: flake8-encodings (==0.5.0.post1) ; extra == 'dev'
Requires-Dist: flake8-expression-complexity (==0.0.11) ; extra == 'dev'
Requires-Dist: flake8-fastapi (==0.7.0) ; extra == 'dev'
Requires-Dist: flake8-helper (==0.2.1) ; extra == 'dev'
Requires-Dist: flake8-import-order (==0.18.1) ; extra == 'dev'
Requires-Dist: flake8-multiline-containers (==0.0.19) ; extra == 'dev'
Requires-Dist: flake8-newspaper-style (==0.3.0) ; extra == 'dev'
Requires-Dist: flake8-pie (==0.15.0) ; extra == 'dev'
Requires-Dist: flake8-plugin-utils (==1.3.2) ; extra == 'dev'
Requires-Dist: flake8-polyfill (==1.0.2) ; extra == 'dev'
Requires-Dist: flake8-quotes (==3.3.1) ; extra == 'dev'
Requires-Dist: flake8-return (==1.1.3) ; extra == 'dev'
Requires-Dist: flake8-scream (==0.1.0) ; extra == 'dev'
Requires-Dist: flake8-simplify (==0.19.3) ; extra == 'dev'
Requires-Dist: flake8-unused-arguments (==0.0.11) ; extra == 'dev'
Requires-Dist: flake8-useless-assert (==0.4.3) ; extra == 'dev'
Requires-Dist: flake8-variables-names (==0.0.5) ; extra == 'dev'
Provides-Extra: test
